extra_metrics/__init__.py
extra_metrics/application.py
extra_metrics/compliance.py
extra_metrics/config.py
extra_metrics/devices.py
extra_metrics/fw_zmq_eventsub.py
extra_metrics/fwrest.py
extra_metrics/logs.py
extra_metrics/main.py
extra_metrics/package.py
extra_metrics/platform.py
extra_metrics/queries.py
extra_metrics/scripts.py
extra_metrics/softwarepatches.py
extra_metrics/app_queries/__init__.py
extra_metrics/app_queries/chrome_win.json
extra_metrics/app_queries/cisco_win.json
extra_metrics/app_queries/firefox_win.json
extra_metrics/app_queries/flash_win.json
extra_metrics/app_queries/java_win.json
extra_metrics/app_queries/office_win.json
extra_metrics/app_queries/reader_win.json
extra_metrics/app_queries/vlc_win.json
extra_metrics/app_queries/zoom_win.json
extra_metrics/cfg/__init__.py
extra_metrics/cfg/com.filewave.extra-metrics.plist
extra_metrics/cfg/extra_metrics.yml
extra_metrics/cfg/extra_metrics_supervisord.conf
extra_metrics/dashboards/__init__.py
extra_metrics/dashboards/extra-metrics-Applications.json
extra_metrics/dashboards/extra-metrics-Deployment.json
extra_metrics/dashboards/extra-metrics-PatchStatus.json
extra_metrics/test/__init__.py
extra_metrics/test/fake_mocks.py
extra_metrics/test/test_applications.py
extra_metrics/test/test_compliance.py
extra_metrics/test/test_configuration.py
extra_metrics/test/test_dashboard_data.py
extra_metrics/test/test_fwrest.py
extra_metrics/test/test_queries.py
extra_metrics/test/test_softwarepatches.py
filewave_extra_metrics-1.0.46.dist-info/LICENSE
filewave_extra_metrics-1.0.46.dist-info/METADATA
filewave_extra_metrics-1.0.46.dist-info/WHEEL
filewave_extra_metrics-1.0.46.dist-info/entry_points.txt
filewave_extra_metrics-1.0.46.dist-info/top_level.txt
filewave_extra_metrics-1.0.46.dist-info/RECORD
