Metadata-Version: 2.1
Name: filewave-extra-metrics
Version: 1.0.46
Summary: An additional module that exposes s/ware patching and metrics information to the built in FileWave dashboard
Home-page: https://github.com/johncclayton/useful_dashboard_info
Author: John Clayton
Author-email: johnc@filewave.com
License: UNKNOWN
Platform: UNKNOWN
Classifier: Programming Language :: Python :: 3
Classifier: License :: OSI Approved :: MIT License
Classifier: Operating System :: OS Independent
Requires-Python: >=3.6
Requires-Dist: requests
Requires-Dist: prometheus-client
Requires-Dist: pandas
Requires-Dist: PyYAML
Requires-Dist: click
Requires-Dist: progressbar2
Requires-Dist: pyzmq
Requires-Dist: asyncio-periodic
